epidemmo/__init__.py
epidemmo/builder.py
epidemmo/factor.py
epidemmo/fit_model.py
epidemmo/flow.py
epidemmo/model.py
epidemmo/model_io.py
epidemmo/stage.py
epidemmo/standard.py
epidemmo-0.2.1.dist-info/METADATA
epidemmo-0.2.1.dist-info/WHEEL
epidemmo-0.2.1.dist-info/licenses/LICENSE
epidemmo-0.2.1.dist-info/RECORD
