Metadata-Version: 2.4
Name: epidemmo
Version: 0.2.1
Summary: A package for compartmental epidemic modelling
Project-URL: Homepage, https://github.com/Paul-NP/EpidemicModel
Author-email: Podzolkov Pavel <ppodzolkoff@gmail.com>
License: MIT License
License-File: LICENSE
Classifier: License :: OSI Approved :: MIT License
Classifier: Natural Language :: Russian
Classifier: Operating System :: OS Independent
Classifier: Programming Language :: Python :: 3
Requires-Python: >=3.10
Requires-Dist: matplotlib
Requires-Dist: numpy
Requires-Dist: pandas
Requires-Dist: prettytable
Requires-Dist: scikit-learn
Requires-Dist: scipy
